{
  "animateLoading": true,
  "borderRadius": "{{appsmith.theme.borderRadius.appBorderRadius}}",
  "bottomRow": 6,
  "boxShadow": "none",
  "buttonColor": "{{appsmith.theme.colors.primaryColor}}",
  "buttonVariant": "PRIMARY",
  "disabledWhenInvalid": false,
  "dynamicBindingPathList": [
    {
      "key": "buttonColor"
    },
    {
      "key": "borderRadius"
    }
  ],
  "dynamicTriggerPathList": [
    {
      "key": "onClick"
    }
  ],
  "isDefaultClickDisabled": true,
  "isDisabled": false,
  "isLoading": false,
  "isVisible": true,
  "key": "nuo727345l",
  "leftColumn": 26,
  "minWidth": 120,
  "mobileBottomRow": 7,
  "mobileLeftColumn": 26,
  "mobileRightColumn": 42,
  "mobileTopRow": 3,
  "needsErrorInfo": false,
  "onClick": "{{ustawrabat.run()}}",
  "parentColumnSpace": 19.90625,
  "parentId": "59rw5mx0bq",
  "parentRowSpace": 10,
  "placement": "CENTER",
  "recaptchaType": "V3",
  "renderMode": "CANVAS",
  "resetFormOnClick": false,
  "responsiveBehavior": "hug",
  "rightColumn": 32,
  "text": "ustaw rabat",
  "topRow": 2,
  "type": "BUTTON_WIDGET",
  "version": 1,
  "widgetId": "dm9yhcrt9c",
  "widgetName": "Button8"
}